{
  "context": {
    "domain": "ONDC:RET10",
    "location": {
      "city": {
        "code": "std:080"
      },
      "country": {
        "code": "IND"
      }
    },
    "action": "status",
    "version": "2.0.2",
    "bap_id": "buyerapp.com",
    "bap_uri": "https://buyerapp.com/grocery",
    "bpp_id": "sellerapp.com",
    "bpp_uri": "https://sellerapp.com/grocery",
    "transaction_id": "9568beb3-265a-4730-be4e-c00ba2e5e30a",
    "message_id": "7b6665ef-88b5-4ca4-b481-c7aa6e169b90",
    "timestamp": "2023-01-08T22:00:30.000Z",
    "ttl": "PT30S"
  },
  "message": {
    "order_id": "O1"
  }
}